mybotapi/__init__.py
mybotapi/client.py
mYBotAPI-0.1.3.dist-info/METADATA
mYBotAPI-0.1.3.dist-info/WHEEL
mYBotAPI-0.1.3.dist-info/top_level.txt
mYBotAPI-0.1.3.dist-info/RECORD
